<annotation>
	<folder>annotated</folder>
	<filename>GP_1a.jpg</filename>
	<path>C:\Users\FodorImo\Documents\LabeledData\all_annotated\annotated\GP_1a.jpg</path>
	<source>
		<database>Unknown</database>
	</source>
	<size>
		<width>3120</width>
		<height>4160</height>
		<depth>3</depth>
	</size>
	<segmented>0</segmented>
	<object>
		<name>4</name>
		<pose>Unspecified</pose>
		<truncated>0</truncated>
		<difficult>0</difficult>
		<bndbox>
			<xmin>559</xmin>
			<ymin>829</ymin>
			<xmax>882</xmax>
			<ymax>1134</ymax>
		</bndbox>
	</object>
	<object>
		<name>75</name>
		<pose>Unspecified</pose>
		<truncated>0</truncated>
		<difficult>0</difficult>
		<bndbox>
			<xmin>1177</xmin>
			<ymin>811</ymin>
			<xmax>1500</xmax>
			<ymax>1138</ymax>
		</bndbox>
	</object>
	<object>
		<name>93</name>
		<pose>Unspecified</pose>
		<truncated>0</truncated>
		<difficult>0</difficult>
		<bndbox>
			<xmin>1532</xmin>
			<ymin>825</ymin>
			<xmax>1814</xmax>
			<ymax>1134</ymax>
		</bndbox>
	</object>
	<object>
		<name>104</name>
		<pose>Unspecified</pose>
		<truncated>0</truncated>
		<difficult>0</difficult>
		<bndbox>
			<xmin>1834</xmin>
			<ymin>825</ymin>
			<xmax>2111</xmax>
			<ymax>1093</ymax>
		</bndbox>
	</object>
</annotation>